cryoforge/__init__.py
cryoforge/generate.py
cryoforge/generatebatched.py
cryoforge/generatebulk.py
cryoforge/ingestitem.py
cryoforge/search_items.py
cryoforge/tooling.py
cryoforge-0.4.0.dist-info/licenses/LICENSE
cryoforge-0.4.0.dist-info/METADATA
cryoforge-0.4.0.dist-info/WHEEL
cryoforge-0.4.0.dist-info/entry_points.txt
cryoforge-0.4.0.dist-info/top_level.txt
cryoforge-0.4.0.dist-info/RECORD
