Metadata-Version: 2.4
Name: cryoforge
Version: 0.4.0
Summary: Metadata genrator for ITS_LIVE velocity scenes
Author-email: Luis Lopez <betolin@gmail.com>
Maintainer-email: Luis Lopez <betolin@gmail.com>
License: MIT
Classifier: Environment :: Console
Classifier: Framework :: IPython
Classifier: Development Status :: 4 - Beta
Classifier: Intended Audience :: Science/Research
Classifier: Operating System :: Microsoft :: Windows
Classifier: Operating System :: MacOS
Classifier: Operating System :: POSIX :: Linux
Classifier: Programming Language :: Python :: 3.10
Classifier: Programming Language :: Python :: 3.11
Classifier: Programming Language :: Python :: 3.12
Classifier: Topic :: Software Development :: Libraries
Classifier: Topic :: Software Development
Classifier: License :: OSI Approved :: MIT License
Requires-Python: >=3.10
License-File: LICENSE
Requires-Dist: xarray>=2024.11
Requires-Dist: xstac>=0.1.0
Requires-Dist: dask>=2024.11
Requires-Dist: distributed>=2024.11
Requires-Dist: earthaccess>=0.14.0
Requires-Dist: virtualizarr
Requires-Dist: kerchunk>=0.2.6
Requires-Dist: h5netcdf>=1.5.0
Requires-Dist: pystac>=1.12.0
Requires-Dist: s3fs>=2022.11
Requires-Dist: fsspec>=2022.11
Requires-Dist: shapely>=2.0.0
Requires-Dist: geojson
Requires-Dist: zarr<=3.0.0a
Requires-Dist: h3
Requires-Dist: stac-geoparquet
Requires-Dist: fastparquet
Requires-Dist: pyarrow
Requires-Dist: obstore
Requires-Dist: arro3-core
Requires-Dist: rustac>=0.8.1
Requires-Dist: duckdb
Requires-Dist: tenacity
Requires-Dist: pystac-client
Requires-Dist: pyproj
Requires-Dist: orjson
Provides-Extra: dev
Requires-Dist: bump-my-version>=0.10.0; extra == "dev"
Requires-Dist: pytest; extra == "dev"
Requires-Dist: jupyterlab>=3.0; extra == "dev"
Requires-Dist: dask-labextension; extra == "dev"
Requires-Dist: ruff>=0.6.3; extra == "dev"
Requires-Dist: uv>=0.4.7; extra == "dev"
Provides-Extra: test
Requires-Dist: zarr<3.0.0a,>=2.12.0; extra == "test"
Requires-Dist: numpy>=1.26.4; extra == "test"
Requires-Dist: pytest>=8.3; extra == "test"
Requires-Dist: pytest-watch>=4.2; extra == "test"
Requires-Dist: python-magic>=0.4; extra == "test"
Requires-Dist: responses>=0.14; extra == "test"
Dynamic: license-file
